LICENSE.txt
MANIFEST.in
README.md
setup.py
pyFaceTrace/__init__.py
pyFaceTrace/demo.py
pyFaceTrace/dowloadTest.py
pyFaceTrace/extractZipFile.py
pyFaceTrace/pyFaceTrace.py
pyFaceTrace/zipFolder.py
pyFaceTrace.egg-info/PKG-INFO
pyFaceTrace.egg-info/SOURCES.txt
pyFaceTrace.egg-info/dependency_links.txt
pyFaceTrace.egg-info/requires.txt
pyFaceTrace.egg-info/top_level.txt