Metadata-Version: 2.1
Name: pyFaceTrace
Version: 5.0.5
Summary: easy Face Recognition for python
Home-page: https://pypi.org/project/pyFaceTrace
Author: KuoYuan Li
Author-email: funny4875@gmail.com
License: UNKNOWN
Keywords: Face recognition,Face Trace
Platform: UNKNOWN
Classifier: License :: OSI Approved :: MIT License
Classifier: Programming Language :: Python :: 3
